[
  {
    "name": "Daggers",
    "type": "Daggers",
    "description": "High attack speed weapons with exceptional DPS. Requires close combat.",
    "pros": ["High Attack Speed", "High DPS", "Fast Combos"],
    "cons": ["Close Range Only", "Low Defense", "High Skill Required"],
    "bestFor": "Aggressive players, high skill ceiling",
    "attackPattern": "Fast stabbing attacks"
  },
  {
    "name": "Straight Swords",
    "type": "Straight Swords",
    "description": "Balanced weapons perfect for beginners. Good damage and speed.",
    "pros": ["Balanced Stats", "Easy to Use", "Versatile"],
    "cons": ["No Specialization", "Average in All Areas"],
    "bestFor": "New players, balanced gameplay",
    "attackPattern": "Standard slashing attacks"
  },
  {
    "name": "Great Swords",
    "type": "Great Swords",
    "description": "Two-handed heavy weapons with massive damage but slow attack speed.",
    "pros": ["High Damage", "Wide Range", "Stagger Enemies"],
    "cons": ["Slow Attack Speed", "High Stamina Cost", "Heavy"],
    "bestFor": "Tank builds, boss fights",
    "attackPattern": "Slow, powerful sweeping attacks"
  },
  {
    "name": "Axes",
    "type": "Axes",
    "description": "High damage one-handed weapons with good balance.",
    "pros": ["High Damage", "Good Range", "Versatile"],
    "cons": ["Moderate Speed", "Medium Stamina Cost"],
    "bestFor": "Damage-focused builds",
    "attackPattern": "Heavy chopping attacks"
  },
  {
    "name": "Great Axes",
    "type": "Great Axes",
    "description": "Massive two-handed axes with extreme burst damage and wide area coverage.",
    "pros": ["Extreme Damage", "Large Range", "High Burst"],
    "cons": ["Very Slow", "High Stamina Cost", "Long Recovery"],
    "bestFor": "Boss fights, crowd control",
    "attackPattern": "Devastating wide swings"
  },
  {
    "name": "Katanas",
    "type": "Katanas",
    "description": "Agile weapons focused on precision strikes and critical hits.",
    "pros": ["High Critical Rate", "Fast Attacks", "Precise"],
    "cons": ["Lower Base Damage", "Requires Skill"],
    "bestFor": "Skill-based players, precision builds",
    "attackPattern": "Quick, precise slashes"
  },
  {
    "name": "Gauntlets",
    "type": "Gauntlets",
    "description": "Close-combat weapons for hand-to-hand combat. High speed and combo potential.",
    "pros": ["Fastest Attacks", "High Combo Potential", "Mobility"],
    "cons": ["Very Close Range", "Low Range", "Requires Positioning"],
    "bestFor": "Aggressive close-combat players",
    "attackPattern": "Rapid punching and kicking combos"
  }
]

